package/__init__.py
package/calculator.py
package/convert_pre.py
package/test.py
timopfey_chirtsov_calc-0.1.dist-info/METADATA
timopfey_chirtsov_calc-0.1.dist-info/WHEEL
timopfey_chirtsov_calc-0.1.dist-info/top_level.txt
timopfey_chirtsov_calc-0.1.dist-info/RECORD
